thkit/__init__.py
thkit/_version.py
thkit/config.py
thkit/io.py
thkit/log.py
thkit/markup.py
thkit/path.py
thkit/pkg.py
thkit/range.py
thkit/stuff.py
thkit/jobman/#retired_code.py
thkit/jobman/__init__.py
thkit/jobman/helper.py
thkit/jobman/submit.py
thkit/jobman/schema/sampleConfig_machine_multi.yml
thkit/jobman/schema/sampleConfig_machine_single.yml
thkit/jobman/schema/schema_machine.yml
thkit-25.12.1.dist-info/METADATA
thkit-25.12.1.dist-info/WHEEL
thkit-25.12.1.dist-info/licenses/LICENSE.md
thkit-25.12.1.dist-info/RECORD
