Metadata-Version: 2.4
Name: thkit
Version: 25.12.1
Summary: The Python package of general utilities.
Project-URL: Homepage, https://thangckt.github.io/thkit_doc
Author-email: "C.Thang Nguyen" <sth@sth.com>
License: MIT License
License-File: LICENSE.md
Classifier: Intended Audience :: Science/Research
Classifier: Operating System :: OS Independent
Classifier: Programming Language :: Python :: 3.10
Classifier: Programming Language :: Python :: 3.11
Classifier: Programming Language :: Python :: 3.12
Classifier: Programming Language :: Python :: 3.13
Classifier: Programming Language :: Python :: 3.14
Classifier: Topic :: Scientific/Engineering :: Physics
Requires-Python: >=3.10
Requires-Dist: cerberus
Requires-Dist: dpdispatcher
Requires-Dist: omegaconf
Requires-Dist: pyyaml
Requires-Dist: requests
Requires-Dist: rich
Provides-Extra: bare
Provides-Extra: test
Requires-Dist: numpy; extra == 'test'
Requires-Dist: pytest; extra == 'test'
Requires-Dist: pytest-cov; extra == 'test'
